[
  {
    "date": "2026-03-02",
    "label": "02.03",
    "sites": 1720,
    "matched": 230,
    "mismatched": 18,
    "op_empty": 497,
    "no_recs": 975,
    "recall": 82,
    "unique_phones": 140,
    "operators": {
      "Светлана": {
        "matched": 109,
        "mismatched": 7,
        "total": 430,
        "recall": 93,
        "unique_phones": 92
      },
      "Елена": {
        "matched": 44,
        "mismatched": 10,
        "total": 430,
        "recall": 52,
        "unique_phones": 62
      },
      "Диана": {
        "matched": 18,
        "mismatched": 0,
        "total": 430,
        "recall": 100,
        "unique_phones": 18
      },
      "Юлия": {
        "matched": 59,
        "mismatched": 1,
        "total": 430,
        "recall": 97,
        "unique_phones": 56
      }
    }
  },
  {
    "date": "2026-03-03",
    "label": "03.03",
    "sites": 1696,
    "matched": 449,
    "mismatched": 44,
    "op_empty": 1153,
    "no_recs": 50,
    "recall": 91,
    "unique_phones": 212,
    "operators": {
      "Светлана": {
        "matched": 135,
        "mismatched": 17,
        "total": 424,
        "recall": 89,
        "unique_phones": 120
      },
      "Елена": {
        "matched": 118,
        "mismatched": 26,
        "total": 424,
        "recall": 81,
        "unique_phones": 103
      },
      "Диана": {
        "matched": 90,
        "mismatched": 0,
        "total": 424,
        "recall": 100,
        "unique_phones": 79
      },
      "Юлия": {
        "matched": 106,
        "mismatched": 1,
        "total": 424,
        "recall": 99,
        "unique_phones": 85
      }
    }
  },
  {
    "date": "2026-03-04",
    "label": "04.03",
    "sites": 1708,
    "matched": 450,
    "mismatched": 68,
    "op_empty": 1094,
    "no_recs": 96,
    "recall": 86,
    "unique_phones": 282,
    "operators": {
      "Светлана": {
        "matched": 128,
        "mismatched": 17,
        "total": 427,
        "recall": 86,
        "unique_phones": 137
      },
      "Елена": {
        "matched": 87,
        "mismatched": 43,
        "total": 427,
        "recall": 67,
        "unique_phones": 123
      },
      "Диана": {
        "matched": 117,
        "mismatched": 3,
        "total": 427,
        "recall": 98,
        "unique_phones": 112
      },
      "Юлия": {
        "matched": 118,
        "mismatched": 5,
        "total": 427,
        "recall": 96,
        "unique_phones": 115
      }
    }
  },
  {
    "date": "2026-03-05",
    "label": "05.03",
    "sites": 1720,
    "matched": 451,
    "mismatched": 15,
    "op_empty": 1100,
    "no_recs": 154,
    "recall": 96,
    "unique_phones": 219,
    "operators": {
      "Светлана": {
        "matched": 136,
        "mismatched": 3,
        "total": 430,
        "recall": 98,
        "unique_phones": 125
      },
      "Елена": {
        "matched": 114,
        "mismatched": 4,
        "total": 430,
        "recall": 95,
        "unique_phones": 110
      },
      "Диана": {
        "matched": 90,
        "mismatched": 5,
        "total": 430,
        "recall": 95,
        "unique_phones": 88
      },
      "Юлия": {
        "matched": 111,
        "mismatched": 3,
        "total": 430,
        "recall": 97,
        "unique_phones": 99
      }
    }
  },
  {
    "date": "2026-03-06",
    "label": "06.03",
    "sites": 1732,
    "matched": 660,
    "mismatched": 17,
    "op_empty": 915,
    "no_recs": 140,
    "recall": 97,
    "unique_phones": 290,
    "operators": {
      "Светлана": {
        "matched": 208,
        "mismatched": 0,
        "total": 433,
        "recall": 100,
        "unique_phones": 201
      },
      "Елена": {
        "matched": 109,
        "mismatched": 13,
        "total": 433,
        "recall": 89,
        "unique_phones": 120
      },
      "Диана": {
        "matched": 146,
        "mismatched": 1,
        "total": 433,
        "recall": 99,
        "unique_phones": 117
      },
      "Юлия": {
        "matched": 197,
        "mismatched": 3,
        "total": 433,
        "recall": 98,
        "unique_phones": 194
      }
    }
  },
  {
    "date": "2026-03-10",
    "label": "10.03",
    "sites": 1716,
    "matched": 330,
    "mismatched": 75,
    "op_empty": 1112,
    "no_recs": 199,
    "recall": 80,
    "unique_phones": 227,
    "operators": {
      "Светлана": {
        "matched": 92,
        "mismatched": 29,
        "total": 429,
        "recall": 74,
        "unique_phones": 114
      },
      "Елена": {
        "matched": 100,
        "mismatched": 13,
        "total": 429,
        "recall": 88,
        "unique_phones": 102
      },
      "Диана": {
        "matched": 62,
        "mismatched": 15,
        "total": 429,
        "recall": 81,
        "unique_phones": 69
      },
      "Юлия": {
        "matched": 76,
        "mismatched": 18,
        "total": 429,
        "recall": 78,
        "unique_phones": 91
      }
    }
  },
  {
    "date": "2026-03-11",
    "label": "11.03",
    "sites": 1696,
    "matched": 227,
    "mismatched": 62,
    "op_empty": 1158,
    "no_recs": 249,
    "recall": 75,
    "unique_phones": 183,
    "operators": {
      "Светлана": {
        "matched": 58,
        "mismatched": 27,
        "total": 424,
        "recall": 67,
        "unique_phones": 79
      },
      "Елена": {
        "matched": 56,
        "mismatched": 8,
        "total": 424,
        "recall": 85,
        "unique_phones": 60
      },
      "Диана": {
        "matched": 51,
        "mismatched": 16,
        "total": 424,
        "recall": 72,
        "unique_phones": 67
      },
      "Юлия": {
        "matched": 62,
        "mismatched": 11,
        "total": 424,
        "recall": 79,
        "unique_phones": 72
      }
    }
  },
  {
    "date": "2026-03-12",
    "label": "12.03",
    "sites": 1728,
    "matched": 230,
    "mismatched": 54,
    "op_empty": 871,
    "no_recs": 573,
    "recall": 73,
    "unique_phones": 174,
    "operators": {
      "Светлана": {
        "matched": 100,
        "mismatched": 23,
        "total": 432,
        "recall": 72,
        "unique_phones": 118
      },
      "Елена": {
        "matched": 39,
        "mismatched": 6,
        "total": 432,
        "recall": 78,
        "unique_phones": 38
      },
      "Диана": {
        "matched": 16,
        "mismatched": 3,
        "total": 432,
        "recall": 84,
        "unique_phones": 17
      },
      "Юлия": {
        "matched": 75,
        "mismatched": 22,
        "total": 432,
        "recall": 69,
        "unique_phones": 89
      }
    }
  }
]